config.py
formatters.py
google_contacts_service.py
main.py
tools.py
mcp_google_contacts_server-0.1.0.dist-info/licenses/LICENSE
mcp_google_contacts_server-0.1.0.dist-info/METADATA
mcp_google_contacts_server-0.1.0.dist-info/WHEEL
mcp_google_contacts_server-0.1.0.dist-info/top_level.txt
mcp_google_contacts_server-0.1.0.dist-info/RECORD
