Metadata-Version: 2.4
Name: mcp-google-contacts-server
Version: 0.1.0
Summary: An MCP server providing Google Contacts integration for AI assistants, allowing contact creation, listing, updating, deletion, and searching capabilities
Author-email: Rayan Zakaria HASSICI <rayan.hassici@ensia.edu.dz>
Requires-Python: >=3.12
License-File: LICENSE
Requires-Dist: httpx>=0.28.1
Requires-Dist: mcp[cli]>=1.5.0
Dynamic: license-file
